MechEngPy/Units.py
MechEngPy/__init__.py
MechEngPy/ComponentDesign/Gears.py
MechEngPy/ComponentDesign/Screws.py
MechEngPy/ComponentDesign/Shafts.py
MechEngPy/ComponentDesign/Solidworks.py
MechEngPy/ComponentDesign/__init__.py
MechEngPy/Dynamic/Fatigue.py
MechEngPy/Dynamic/__init__.py
MechEngPy/Static/Loads.py
MechEngPy/Static/Stress.py
MechEngPy/Static/__init__.py
MechEngPy-0.0.5.dist-info/METADATA
MechEngPy-0.0.5.dist-info/WHEEL
MechEngPy-0.0.5.dist-info/top_level.txt
MechEngPy-0.0.5.dist-info/RECORD
