Metadata-Version: 2.1
Name: MechEngPy
Version: 0.0.5
Summary: UNKNOWN
Home-page: https://github.com/valtervg13/MechPy/tree/main/MechPy
Author: Valter Alvares Gonzaga Filho
Author-email: valtergonzagafilho@gmail.com
License: GPT-3
Keywords: Mechanical Engineering,Engineering,Mechanical Design,Machine Design
Platform: UNKNOWN
Requires-Dist: NumPy
Requires-Dist: MatPlotLib
Requires-Dist: Scipy
Requires-Dist: Pandas
